pypkgs_yg/__init__.py
pypkgs_yg/pypkgs_yg.py
pypkgs_yg-0.1.0.dist-info/LICENSE
pypkgs_yg-0.1.0.dist-info/WHEEL
pypkgs_yg-0.1.0.dist-info/METADATA
pypkgs_yg-0.1.0.dist-info/RECORD
